mttools_lib/__init__.py
mttools_lib/py.typed
mttools_lib/configs/__init__.py
mttools_lib/fio/__init__.py
mttools_lib/fio/base.py
mttools_lib/fio/errors.py
mttools_lib/fio/utils.py
mttools_lib/fio/instruments/__init__.py
mttools_lib/fio/instruments/dart.py
mttools_lib/fio/instruments/errors.py
mttools_lib/fio/instruments/nims.py
mttools_lib/process/__init__.py
mttools_lib/process/utils.py
mttools_lib/process/emtf/__init__.py
mttools_lib/process/emtf/dnff.py
mttools_lib/process/emtf/tranmt.py
mttools_lib/utils/__init__.py
mttools_lib/utils/decimate.py
mttools_lib/utils/nmea.py
mttools_lib/utils/rotate.py
mttools_lib-0.1.0.dist-info/METADATA
mttools_lib-0.1.0.dist-info/WHEEL
mttools_lib-0.1.0.dist-info/licenses/LICENSE
mttools_lib-0.1.0.dist-info/RECORD
